{
  "resource": "2gis",
  "schools": [
    {
      "id": "1",
      "name": "Средняя школа №83",
      "full_name": "МОУ Средняя общеобразовательная школа №83",
      "adres": "Целинстрой м-н, Заводской район, Саратов, 410039. Инфо",
      "rating_2gis": "2.7",
      "url": "https://2gis.ru/saratov/firm/70000001037362342"
    }
  ],
  "reviews": [
    {
      "school_id": "1",
      "date": "27 февраля 2025",
      "text": "Она скоро рухнет вместе с детьми просим наше правителтсьво пожалеть наших детей и граждан г Саратова закройте ее в срочном порядке она опасна для жизни",
      "weightы": true
    },
    {
      "school_id": "1",
      "date": "11 октября 2023, отредактирован",
      "text": "школа несомненно требует ремонта, по крайней мере, на тот момент, пока я там обучалась. в остальном, могу сказать так – там одни из лучших преподавателей по заводскому району, которые действительно учат. не могу выделить конкретного учителя, ведь все невероятно классные!",
      "weightы": true
    }
  ]
}